{
    "kind": "collectionType",
    "collectionName": "questions",
    "info": {
        "singularName": "question",
        "pluralName": "questions",
        "displayName": "Question",
        "description": "MCQ or question definitions"
    },
    "options": {
        "draftAndPublish": false
    },
    "attributes": {
        "question": {
            "type": "text"
        },
        "options": {
            "type": "json"
        },
        "correctAnswer": {
            "type": "integer"
        },
        "topic": {
            "type": "relation",
            "relation": "manyToOne",
            "target": "api::topic.topic",
            "inversedBy": "questions"
        },
        "question_nodes": {
            "type": "relation",
            "relation": "oneToMany",
            "target": "api::question-node.question-node",
            "mappedBy": "question"
        }
    }
}